statsd.py
statsd_client-1.0.7.dist-info/LICENSE
statsd_client-1.0.7.dist-info/METADATA
statsd_client-1.0.7.dist-info/NOTICE
statsd_client-1.0.7.dist-info/WHEEL
statsd_client-1.0.7.dist-info/top_level.txt
statsd_client-1.0.7.dist-info/RECORD
