Metadata-Version: 2.1
Name: statsd-client
Version: 1.0.7
Summary: StatsD client for Python
Home-page: https://github.com/gaelenh/python-statsd-client
Author: Gaelen Hadlett
Author-email: gaelenh@gmail.com
License: Apache 2.0
Keywords: statsd,graphite,stats
Platform: UNKNOWN
Classifier: License :: OSI Approved :: Apache Software License
Classifier: Programming Language :: Python :: 2.6
Classifier: Programming Language :: Python :: 2.7
Classifier: Programming Language :: Python :: 3
Classifier: Topic :: System :: Logging
Classifier: Operating System :: MacOS :: MacOS X
Classifier: Operating System :: POSIX :: Linux
Classifier: Operating System :: Unix
Classifier: Intended Audience :: Developers
